setup.py
shinkenplugins/__init__.py
shinkenplugins.plugins.reseaucontactcom.egg-info/PKG-INFO
shinkenplugins.plugins.reseaucontactcom.egg-info/SOURCES.txt
shinkenplugins.plugins.reseaucontactcom.egg-info/dependency_links.txt
shinkenplugins.plugins.reseaucontactcom.egg-info/entry_points.txt
shinkenplugins.plugins.reseaucontactcom.egg-info/namespace_packages.txt
shinkenplugins.plugins.reseaucontactcom.egg-info/requires.txt
shinkenplugins.plugins.reseaucontactcom.egg-info/top_level.txt
shinkenplugins/plugins/__init__.py
shinkenplugins/plugins/reseaucontactcom/__init__.py
shinkenplugins/plugins/reseaucontactcom/reseaucontactcom.py