Metadata-Version: 1.0
Name: shinkenplugins.plugins.reseaucontactcom
Version: 0.1
Summary: Check Redis
Home-page: https://github.com/savoirfairelinux/monitoring-tools
Author: Savoir-faire Linux
Author-email: supervision@savoirfairelinux.com
License: GPL3+
Platform: any
